hello_world/__init__.py
hello_world/tools/__init__.py
hello_world/tools/hello_world_tool.py
hello_world/tools/hello_world_tool_2.py
hello_world/tools/utils.py
hello_world/yamls/hello_world_tool.yaml
hello_world/yamls/hello_world_tool2.yaml
tests/__init__.py
tests/test_hello_world_tool.py
yao_hello_world-0.0.2.dist-info/METADATA
yao_hello_world-0.0.2.dist-info/WHEEL
yao_hello_world-0.0.2.dist-info/entry_points.txt
yao_hello_world-0.0.2.dist-info/top_level.txt
yao_hello_world-0.0.2.dist-info/RECORD
