Metadata-Version: 2.1
Name: yao-hello-world
Version: 0.0.2
Summary: This is my tools package
